{
  "base_url": "https://samnorflutter.github.io/alphaplast-site",
  "metrika_id": "110515862",
  "ga_id": "G-MNCSCKFW9M",
  "chat_src": "https://embed.tawk.to/6a4e87d4a6558f1d451fd549/1jt1c55mr",
  "instagram_posts": [
    "https://www.instagram.com/p/DXwJvUPM4cJ/",
    "https://www.instagram.com/p/DQEZ62cjEHU/",
    "https://www.instagram.com/p/DATTOIDNn4T/",
    "https://www.instagram.com/p/DZz9oRfNIMC/",
    "https://www.instagram.com/p/DaVJM-aMSgj/",
    "https://www.instagram.com/p/DQcGBh_DDcu/"
  ],
  "instagram_profile": {
    "name": "Alpha Plast",
    "handle": "alphaplast_uz",
    "posts": "",
    "followers": "",
    "following": ""
  }
}
